bootstrapped/__init__.py
bootstrapped/bootstrap.py
bootstrapped/compare_functions.py
bootstrapped/power.py
bootstrapped/stats_functions.py
bootstrapped-0.0.1.dist-info/DESCRIPTION.rst
bootstrapped-0.0.1.dist-info/METADATA
bootstrapped-0.0.1.dist-info/RECORD
bootstrapped-0.0.1.dist-info/WHEEL
bootstrapped-0.0.1.dist-info/metadata.json
bootstrapped-0.0.1.dist-info/top_level.txt
