Metadata-Version: 2.0
Name: bootstrapped
Version: 0.0.1
Summary: Implementations of the percentile based bootstrap
Home-page: https://github.com/facebookincubator/bootstrapped
Author: Spencer Beecher
Author-email: spencebeecher@gmail.com
License: UNKNOWN
Platform: UNKNOWN
Requires-Dist: matplotlib (==1.5.3)
Requires-Dist: numpy (==1.11.1)
Requires-Dist: pandas (==0.18.1)
